wafer/__init__.py
wafer/fields.py
wafer/repository.py
wafer/utils.py
wafer/validators.py
geekie_wafer-3.0.0.dist-info/LICENSE
geekie_wafer-3.0.0.dist-info/METADATA
geekie_wafer-3.0.0.dist-info/WHEEL
geekie_wafer-3.0.0.dist-info/top_level.txt
geekie_wafer-3.0.0.dist-info/RECORD
