Metadata-Version: 2.1
Name: geekie-wafer
Version: 3.0.0
Requires-Python: >=3.7
License-File: LICENSE
Requires-Dist: six <2,>=1.16.0
